czelta.cpython-36m-x86_64-linux-gnu.so
czelta-1.0.dist-info/METADATA
czelta-1.0.dist-info/RECORD
czelta-1.0.dist-info/WHEEL
czelta-1.0.dist-info/top_level.txt
opt/_internal/cpython-3.6.9/lib/python3.6/site-packages/LICENSE.txt
opt/_internal/cpython-3.6.9/lib/python3.6/site-packages/config_data.JSON
