Metadata-Version: 2.1
Name: czelta
Version: 1.0
Summary: Analysis libraty for project CZELTA (http://czelta.utef.cvut.cz/)
Home-page: https://github.com/Hinogary/czelta-python/
Author: Martin Quarda
Author-email: hinogary@gmail.com
License: LICENSE.txt
Keywords: czelta cosmic rays
Platform: UNKNOWN
Classifier: Framework :: Sphinx
Classifier: Framework :: Pytest
Classifier: Intended Audience :: Developers
Classifier: License :: OSI Approved :: GNU General Public License v3 (GPLv3)
Classifier: Programming Language :: Cython
Classifier: Programming Language :: C++
Classifier: Topic :: Scientific/Engineering :: Physics
Requires-Dist: scipy
Requires-Dist: PyYAML
